etc/idiotic/conf.json
idiotic/__init__.py
idiotic/__main__.py
idiotic/declare.py
idiotic/dispatch.py
idiotic/event.py
idiotic/history.py
idiotic/item.py
idiotic/main.py
idiotic/modutils.py
idiotic/persistence.py
idiotic/rule.py
idiotic/scene.py
idiotic/timer.py
idiotic/distrib/__init__.py
idiotic/distrib/base.py
idiotic/distrib/udp.py
idiotic/utils/__init__.py
idiotic/utils/api.py
idiotic/utils/etc.py
idiotic/utils/load.py
idiotic-0.2.0.dist-info/DESCRIPTION.rst
idiotic-0.2.0.dist-info/METADATA
idiotic-0.2.0.dist-info/RECORD
idiotic-0.2.0.dist-info/WHEEL
idiotic-0.2.0.dist-info/entry_points.txt
idiotic-0.2.0.dist-info/metadata.json
idiotic-0.2.0.dist-info/top_level.txt
usr/lib/idiotic/modules/api.py
usr/lib/idiotic/modules/sql.py
usr/lib/idiotic/modules/__pycache__/api.cpython-35.pyc
usr/lib/idiotic/modules/__pycache__/sql.cpython-35.pyc
usr/lib/systemd/system/idiotic.service
