Metadata-Version: 2.0
Name: idiotic
Version: 0.2.0
Summary: Distributed home automation controller
Home-page: https://github.com/umbc-hackafe/idiotic
Author: Dylan Whichard
Author-email: dylan@whichard.com
License: The MIT License (MIT)
Requires-Dist: Flask (>=0.10.1)
Requires-Dist: aiohttp (>=0.21.2)
Requires-Dist: docopt (>=0.6.2)
Requires-Dist: schedule (>=0.3.2)
Requires-Dist: werkzeug (>=0.11.4)
